{
  "$schema": "https://vega.github.io/schema/vega-lite/v6.json",
 
"title": {
  "text": "South Korea's total fertility rate",
  "subtitle": "Source: UN Population Division via World Bank"
},

  "data": {"url": "https://api.worldbank.org/v2/country/kor;prk/indicator/SP.DYN.TFRT.IN?format=json&date=1960:2025&per_page=160",
  "format":{
    "property": "[1]"

  }
  },

  "mark": "line",

  "encoding": {
    "x": {"field": "date", "type": "temporal", "axis":{ "grid":false} },
    "color": {"field": "countryiso3code", "title": "Country"},
    "y": {"field": "value", "type": "quantitative", "title":"TRF", "axis": {
      "titleAlign": "center"
    }}
  }
}